vnumpy/__init__.py
vnumpy/v3d.py
vnumpy/v_dll/v.dll
vnumpy-0.1.6.dist-info/LICENSE
vnumpy-0.1.6.dist-info/METADATA
vnumpy-0.1.6.dist-info/WHEEL
vnumpy-0.1.6.dist-info/top_level.txt
vnumpy-0.1.6.dist-info/RECORD
